agg/__init__.py
agg/__main__.py
agg/py.typed
agg-0.3.1.dist-info/LICENSE
agg-0.3.1.dist-info/METADATA
agg-0.3.1.dist-info/WHEEL
agg-0.3.1.dist-info/top_level.txt
agg-0.3.1.dist-info/RECORD
